jzx_env/__init__.py
jzx_env/envs/__init__.py
jzx_env/envs/env_jzx.py
jzx_env-0.0.1.dist-info/METADATA
jzx_env-0.0.1.dist-info/WHEEL
jzx_env-0.0.1.dist-info/top_level.txt
jzx_env-0.0.1.dist-info/RECORD
