Metadata-Version: 2.1
Name: jzx-env
Version: 0.0.1
Summary: A OpenAI Gym Env for jzx
Requires-Dist: gym
